LICENSE.txt
MANIFEST.in
README.md
setup.py
csv_overview/__init__.py
csv_overview.egg-info/PKG-INFO
csv_overview.egg-info/SOURCES.txt
csv_overview.egg-info/dependency_links.txt
csv_overview.egg-info/not-zip-safe
csv_overview.egg-info/top_level.txt
scripts/csv-overview