Metadata-Version: 1.1
Name: csv-overview
Version: 0.32
Summary: Get the vital statistics of a CSV file
Home-page: http://github.com/sbirch/csv-overview
Author: Sam Birch
Author-email: sam.m.birch@gmail.com
License: MIT
Platform: UNKNOWN
Classifier: License :: OSI Approved :: MIT License
Classifier: Programming Language :: Python :: 2.7
Classifier: Development Status :: 3 - Alpha
